drf_weasyprint/__init__.py
drf_weasyprint/mixins.py
drf_weasyprint/renderers.py
drf_weasyprint/settings.py
drf_weasyprint-1.0.2.dist-info/licenses/LICENSE
drf_weasyprint-1.0.2.dist-info/METADATA
drf_weasyprint-1.0.2.dist-info/WHEEL
drf_weasyprint-1.0.2.dist-info/top_level.txt
drf_weasyprint-1.0.2.dist-info/RECORD
