Metadata-Version: 2.4
Name: drf_weasyprint
Version: 1.0.2
Summary: A Django REST Framework package for generating PDF files with WeasyPrint.
Home-page: https://github.com/yasco1/drf_weasyprint
Author: Mohamed Yassin (yasco1)
Author-email: muhamad_yassin@hotmail.com
Classifier: Programming Language :: Python :: 3
Classifier: License :: OSI Approved :: MIT License
Requires-Python: >=3.9
License-File: LICENSE
Requires-Dist: djangorestframework>=3.14.0
Requires-Dist: weasyprint>=65.1
Dynamic: author
Dynamic: author-email
Dynamic: classifier
Dynamic: description
Dynamic: description-content-type
Dynamic: home-page
Dynamic: license-file
Dynamic: requires-dist
Dynamic: requires-python
Dynamic: summary
